kinematics_library/__init__.py
kinematics_library/_add_docs.py
kinematics_library/_helpers.py
kinematics_library/kinematics_library.pyd
kinematics_library/kinematics_library.pyi
kinematics_library/version.py
kinematics_library/transforms/__init__.py
kinematics_library/transforms/transforms.pyd
kinematics_library/transforms/transforms.pyi
kinematics_library-1.1.4.dist-info/METADATA
kinematics_library-1.1.4.dist-info/WHEEL
kinematics_library-1.1.4.dist-info/top_level.txt
kinematics_library-1.1.4.dist-info/RECORD
